sprite_sheet/spriteutil.py
spriteutil_intek_2020_nqcuong96-1.0.0.dist-info/LICENSE
spriteutil_intek_2020_nqcuong96-1.0.0.dist-info/METADATA
spriteutil_intek_2020_nqcuong96-1.0.0.dist-info/WHEEL
spriteutil_intek_2020_nqcuong96-1.0.0.dist-info/top_level.txt
spriteutil_intek_2020_nqcuong96-1.0.0.dist-info/RECORD
