Metadata-Version: 2.1
Name: spriteutil-intek-2020-nqcuong96
Version: 1.0.0
Summary: UNKNOWN
Home-page: https://github.com/intek-training-jsc/sprite-sheet-nqcuong96
Author: Nguyen Quang Cuong
Author-email: cuong.nguyen@f4.intek.edu.vn
License: MIT
Platform: UNKNOWN
Classifier: Programming Language :: Python :: 3
Classifier: License :: OSI Approved :: MIT License
Classifier: Operating System :: OS Independent
Requires-Python: >=3.7
Requires-Dist: numpy (==1.18.1)
Requires-Dist: pillow (==7.0.0)
Requires-Dist: setuptools (==45.0.0)
Requires-Dist: wheel (==0.33.6)
Requires-Dist: twine (==3.1.1)
Requires-Dist: pipfile (==0.0.2)
